changelog/.gitempty
dkist_dev_tools/__init__.py
dkist_dev_tools/allowed_freezing_services.py
dkist_dev_tools/changelog.py
dkist_dev_tools/cli.py
dkist_dev_tools/console.py
dkist_dev_tools/freeze_dependencies.py
dkist_dev_tools/get_pyproject_toml.py
dkist_dev_tools/git.py
dkist_dev_tools/prod_python_version.py
dkist_dev_tools/version_type.py
dkist_dev_tools/tests/__init__.py
dkist_dev_tools/tests/conftest.py
dkist_dev_tools/tests/test_changelog.py
dkist_dev_tools/tests/test_check_changelog.py
dkist_dev_tools/tests/test_check_freeze.py
dkist_dev_tools/tests/test_freeze.py
dkist_dev_tools/tests/test_version_type.py
licenses/LICENSE.rst
licenses/README.rst
dkist_dev_tools-2.0.0.dist-info/METADATA
dkist_dev_tools-2.0.0.dist-info/WHEEL
dkist_dev_tools-2.0.0.dist-info/entry_points.txt
dkist_dev_tools-2.0.0.dist-info/top_level.txt
dkist_dev_tools-2.0.0.dist-info/RECORD
