Metadata-Version: 2.4
Name: dkist-dev-tools
Version: 2.0.0
Summary: Toolkit for developers of the `dkist-processing-*` stack.
Author-email: NSO / AURA <dkistdc@nso.edu>
License: BSD-3-Clause
Project-URL: Homepage, https://nso.edu/dkist/data-center/
Project-URL: Repository, https://bitbucket.org/dkistdc/dkist-dev-tools/
Project-URL: Documentation, https://bitbucket.org/dkistdc/dkist-dev-tools/
Project-URL: Help, https://nso.atlassian.net/servicedesk/customer/portal/5
Classifier: Programming Language :: Python
Classifier: Programming Language :: Python :: 3
Classifier: Programming Language :: Python :: 3.12
Requires-Python: >=3.12
Requires-Dist: tomlkit>=0.9.0
Requires-Dist: click>=8.0.0
Requires-Dist: rich>=10.0.0
Requires-Dist: packaging>=24.2
Requires-Dist: towncrier>=24.8.0
Provides-Extra: test
Requires-Dist: pytest; extra == "test"
Requires-Dist: pytest-cov; extra == "test"
Requires-Dist: pytest-mock; extra == "test"
Requires-Dist: pytest-xdist; extra == "test"
Requires-Dist: tox>=4; extra == "test"
